{
  "family": {
    "id": "rockicon",
    "name": "Rockicon",
    "slug": "rockicon",
    "authors": [
      {
        "name": ""
      }
    ],
    "license": "mit",
    "defaultTier": "free",
    "status": "published",
    "bundles": [
      {
        "id": "outline",
        "name": "Outline",
        "strokeBased": true,
        "predefined": true
      }
    ],
    "categories": [
      {
        "id": "arrow",
        "name": "Arrow",
        "subcategories": []
      },
      {
        "id": "shopping",
        "name": "Shopping",
        "subcategories": [
          {
            "id": "cart",
            "name": "Cart"
          }
        ]
      }
    ]
  },
  "icons": [
    {
      "id": "rockicon__barcode",
      "familyId": "rockicon",
      "name": "barcode",
      "categoryId": "arrow",
      "tags": [
        "barcode"
      ],
      "tier": "free",
      "status": "published",
      "variants": [
        {
          "bundleId": "outline",
          "viewBox": "0 0 24 24",
          "paths": [
            {
              "tag": "circle",
              "attrs": {
                "cx": "16",
                "cy": "17",
                "r": "1"
              }
            },
            {
              "tag": "circle",
              "attrs": {
                "cx": "12",
                "cy": "17",
                "r": "1"
              }
            },
            {
              "tag": "circle",
              "attrs": {
                "cx": "8",
                "cy": "17",
                "r": "1"
              }
            },
            {
              "tag": "path",
              "attrs": {
                "d": "M20 7v10M16 7v6M12 7v6M8 7v6M4 7v10"
              }
            }
          ],
          "strokeBased": true
        }
      ]
    },
    {
      "id": "rockicon__scan-barcode-01",
      "familyId": "rockicon",
      "name": "scan barcode 01",
      "categoryId": "arrow",
      "tags": [
        "scan",
        "barcode",
        "01"
      ],
      "tier": "free",
      "status": "published",
      "variants": [
        {
          "bundleId": "outline",
          "viewBox": "0 0 24 24",
          "paths": [
            {
              "tag": "path",
              "attrs": {
                "d": "M12 14v1M16 8v7M12 8v2M8 8v7M18 5h2v13h-2M6 5H4v13h2"
              }
            }
          ],
          "strokeBased": true
        }
      ]
    },
    {
      "id": "rockicon__scan-barcode-02",
      "familyId": "rockicon",
      "name": "scan barcode 02",
      "categoryId": "arrow",
      "tags": [
        "scan",
        "barcode",
        "02"
      ],
      "tier": "free",
      "status": "published",
      "variants": [
        {
          "bundleId": "outline",
          "viewBox": "0 0 24 24",
          "paths": [
            {
              "tag": "path",
              "attrs": {
                "d": "M20 16v2h-2M4 16v2h2M12 14v1M16 8v7M12 8v2M8 8v7M18 5h2v2M6 5H4v2"
              }
            }
          ],
          "strokeBased": true
        }
      ]
    },
    {
      "id": "rockicon__cart-01",
      "familyId": "rockicon",
      "name": "cart 01",
      "categoryId": "shopping",
      "subcategoryId": "cart",
      "tags": [
        "cart",
        "01"
      ],
      "tier": "free",
      "status": "published",
      "variants": [
        {
          "bundleId": "outline",
          "viewBox": "0 0 24 24",
          "paths": [
            {
              "tag": "path",
              "attrs": {
                "d": "M17.5 21a1.5 1.5 0 1 0 0-3 1.5 1.5 0 0 0 0 3M8.5 21a1.5 1.5 0 1 0 0-3 1.5 1.5 0 0 0 0 3"
              }
            },
            {
              "tag": "path",
              "attrs": {
                "d": "M7 18h12M8 7h11l-1 7H8L7 4H5"
              }
            }
          ],
          "strokeBased": true
        }
      ]
    },
    {
      "id": "rockicon__cart-add-01",
      "familyId": "rockicon",
      "name": "cart add 01",
      "categoryId": "shopping",
      "subcategoryId": "cart",
      "tags": [
        "cart",
        "add",
        "01"
      ],
      "tier": "free",
      "status": "published",
      "variants": [
        {
          "bundleId": "outline",
          "viewBox": "0 0 24 24",
          "paths": [
            {
              "tag": "path",
              "attrs": {
                "d": "M16.5 21a1.5 1.5 0 1 0 0-3 1.5 1.5 0 0 0 0 3M7.5 21a1.5 1.5 0 1 0 0-3 1.5 1.5 0 0 0 0 3"
              }
            },
            {
              "tag": "path",
              "attrs": {
                "d": "M6 18h12"
              }
            },
            {
              "tag": "circle",
              "attrs": {
                "cx": "17",
                "cy": "6",
                "r": "4"
              }
            },
            {
              "tag": "path",
              "attrs": {
                "d": "M17 4v4m-2-2h4"
              }
            },
            {
              "tag": "path",
              "attrs": {
                "d": "M4 4h2l1 10h10l.14-1M7 7h3"
              }
            }
          ],
          "strokeBased": true
        }
      ]
    },
    {
      "id": "rockicon__cart-apply-01",
      "familyId": "rockicon",
      "name": "cart apply 01",
      "categoryId": "shopping",
      "subcategoryId": "cart",
      "tags": [
        "cart",
        "apply",
        "01"
      ],
      "tier": "free",
      "status": "published",
      "variants": [
        {
          "bundleId": "outline",
          "viewBox": "0 0 24 24",
          "paths": [
            {
              "tag": "path",
              "attrs": {
                "d": "M16.5 21a1.5 1.5 0 1 0 0-3 1.5 1.5 0 0 0 0 3M7.5 21a1.5 1.5 0 1 0 0-3 1.5 1.5 0 0 0 0 3"
              }
            },
            {
              "tag": "path",
              "attrs": {
                "d": "M18 18H6"
              }
            },
            {
              "tag": "circle",
              "attrs": {
                "cx": "17",
                "cy": "6",
                "r": "4"
              }
            },
            {
              "tag": "path",
              "attrs": {
                "d": "m15 6.2 1.5 1.5L19 4.8"
              }
            },
            {
              "tag": "path",
              "attrs": {
                "d": "M4 4h2l1 10h10l.14-1M7 7h3"
              }
            }
          ],
          "strokeBased": true
        }
      ]
    },
    {
      "id": "rockicon__cart-broken-01",
      "familyId": "rockicon",
      "name": "cart broken 01",
      "categoryId": "shopping",
      "subcategoryId": "cart",
      "tags": [
        "cart",
        "broken",
        "01"
      ],
      "tier": "free",
      "status": "published",
      "variants": [
        {
          "bundleId": "outline",
          "viewBox": "0 0 24 24",
          "paths": [
            {
              "tag": "path",
              "attrs": {
                "d": "M17.5 21a1.5 1.5 0 1 0 0-3 1.5 1.5 0 0 0 0 3M8.5 21a1.5 1.5 0 1 0 0-3 1.5 1.5 0 0 0 0 3"
              }
            },
            {
              "tag": "path",
              "attrs": {
                "d": "M6 18h14M5 4h2l1 10h10l1-7h-5l-2 1.5 2 1-2 2M8 7h1.5"
              }
            }
          ],
          "strokeBased": true
        }
      ]
    },
    {
      "id": "rockicon__cart-error-01",
      "familyId": "rockicon",
      "name": "cart error 01",
      "categoryId": "shopping",
      "subcategoryId": "cart",
      "tags": [
        "cart",
        "error",
        "01"
      ],
      "tier": "free",
      "status": "published",
      "variants": [
        {
          "bundleId": "outline",
          "viewBox": "0 0 24 24",
          "paths": [
            {
              "tag": "path",
              "attrs": {
                "d": "M16.5 21a1.5 1.5 0 1 0 0-3 1.5 1.5 0 0 0 0 3M7.5 21a1.5 1.5 0 1 0 0-3 1.5 1.5 0 0 0 0 3"
              }
            },
            {
              "tag": "path",
              "attrs": {
                "d": "M18 18H6"
              }
            },
            {
              "tag": "circle",
              "attrs": {
                "cx": "17",
                "cy": "6",
                "r": "4"
              }
            },
            {
              "tag": "path",
              "attrs": {
                "d": "m15.5 4.5 3 3m0-3-3 3"
              }
            },
            {
              "tag": "path",
              "attrs": {
                "d": "M4 4h2l1 10h10l.14-1M7 7h3"
              }
            }
          ],
          "strokeBased": true
        }
      ]
    },
    {
      "id": "rockicon__cart-favourite-01",
      "familyId": "rockicon",
      "name": "cart favourite 01",
      "categoryId": "shopping",
      "subcategoryId": "cart",
      "tags": [
        "cart",
        "favourite",
        "01"
      ],
      "tier": "free",
      "status": "published",
      "variants": [
        {
          "bundleId": "outline",
          "viewBox": "0 0 24 24",
          "paths": [
            {
              "tag": "path",
              "attrs": {
                "d": "M16.5 21a1.5 1.5 0 1 0 0-3 1.5 1.5 0 0 0 0 3M7.5 21a1.5 1.5 0 1 0 0-3 1.5 1.5 0 0 0 0 3"
              }
            },
            {
              "tag": "path",
              "attrs": {
                "d": "M18 18H6"
              }
            },
            {
              "tag": "circle",
              "attrs": {
                "cx": "17",
                "cy": "6",
                "r": "4"
              }
            },
            {
              "tag": "path",
              "attrs": {
                "d": "M17 8.3S14.6 6.7 14.6 5c0-.9.7-1.6 1.6-1.6.3 0 .6.2.8.5.2-.3.5-.5.8-.5.9 0 1.6.7 1.6 1.6 0 1.7-2.4 3.3-2.4 3.3"
              }
            },
            {
              "tag": "path",
              "attrs": {
                "d": "M4 4h2l1 10h10l.14-1M7 7h3"
              }
            }
          ],
          "strokeBased": true
        }
      ]
    },
    {
      "id": "rockicon__cart-load-01",
      "familyId": "rockicon",
      "name": "cart load 01",
      "categoryId": "shopping",
      "subcategoryId": "cart",
      "tags": [
        "cart",
        "load",
        "01"
      ],
      "tier": "free",
      "status": "published",
      "variants": [
        {
          "bundleId": "outline",
          "viewBox": "0 0 24 24",
          "paths": [
            {
              "tag": "path",
              "attrs": {
                "d": "M16.5 21a1.5 1.5 0 1 0 0-3 1.5 1.5 0 0 0 0 3M7.5 21a1.5 1.5 0 1 0 0-3 1.5 1.5 0 0 0 0 3"
              }
            },
            {
              "tag": "path",
              "attrs": {
                "d": "M18 18H6"
              }
            },
            {
              "tag": "circle",
              "attrs": {
                "cx": "17",
                "cy": "6",
                "r": "4"
              }
            },
            {
              "tag": "path",
              "attrs": {
                "d": "M17 3.8v4.4m-2-2 2 2 2-2"
              }
            },
            {
              "tag": "path",
              "attrs": {
                "d": "M4 4h2l1 10h10l.14-1M7 7h3"
              }
            }
          ],
          "strokeBased": true
        }
      ]
    },
    {
      "id": "rockicon__cart-remove-01",
      "familyId": "rockicon",
      "name": "cart remove 01",
      "categoryId": "shopping",
      "subcategoryId": "cart",
      "tags": [
        "cart",
        "remove",
        "01"
      ],
      "tier": "free",
      "status": "published",
      "variants": [
        {
          "bundleId": "outline",
          "viewBox": "0 0 24 24",
          "paths": [
            {
              "tag": "path",
              "attrs": {
                "d": "M16.5 21a1.5 1.5 0 1 0 0-3 1.5 1.5 0 0 0 0 3M7.5 21a1.5 1.5 0 1 0 0-3 1.5 1.5 0 0 0 0 3"
              }
            },
            {
              "tag": "path",
              "attrs": {
                "d": "M6 18h12"
              }
            },
            {
              "tag": "circle",
              "attrs": {
                "cx": "17",
                "cy": "6",
                "r": "4"
              }
            },
            {
              "tag": "path",
              "attrs": {
                "d": "M15 6h4"
              }
            },
            {
              "tag": "path",
              "attrs": {
                "d": "M4 4h2l1 10h10l.14-1M7 7h3"
              }
            }
          ],
          "strokeBased": true
        }
      ]
    },
    {
      "id": "rockicon__cart-unload-01",
      "familyId": "rockicon",
      "name": "cart unload 01",
      "categoryId": "shopping",
      "subcategoryId": "cart",
      "tags": [
        "cart",
        "unload",
        "01"
      ],
      "tier": "free",
      "status": "published",
      "variants": [
        {
          "bundleId": "outline",
          "viewBox": "0 0 24 24",
          "paths": [
            {
              "tag": "path",
              "attrs": {
                "d": "M16.5 21a1.5 1.5 0 1 0 0-3 1.5 1.5 0 0 0 0 3M7.5 21a1.5 1.5 0 1 0 0-3 1.5 1.5 0 0 0 0 3"
              }
            },
            {
              "tag": "path",
              "attrs": {
                "d": "M18 18H6"
              }
            },
            {
              "tag": "circle",
              "attrs": {
                "cx": "17",
                "cy": "6",
                "r": "4"
              }
            },
            {
              "tag": "path",
              "attrs": {
                "d": "M17 8.2V3.8m-2 2 2-2 2 2"
              }
            },
            {
              "tag": "path",
              "attrs": {
                "d": "M4 4h2l1 10h10l.14-1M7 7h3"
              }
            }
          ],
          "strokeBased": true
        }
      ]
    },
    {
      "id": "rockicon__cart-waiting-01",
      "familyId": "rockicon",
      "name": "cart waiting 01",
      "categoryId": "shopping",
      "subcategoryId": "cart",
      "tags": [
        "cart",
        "waiting",
        "01"
      ],
      "tier": "free",
      "status": "published",
      "variants": [
        {
          "bundleId": "outline",
          "viewBox": "0 0 24 24",
          "paths": [
            {
              "tag": "path",
              "attrs": {
                "d": "M16.5 21a1.5 1.5 0 1 0 0-3 1.5 1.5 0 0 0 0 3M7.5 21a1.5 1.5 0 1 0 0-3 1.5 1.5 0 0 0 0 3"
              }
            },
            {
              "tag": "path",
              "attrs": {
                "d": "M18 18H6"
              }
            },
            {
              "tag": "circle",
              "attrs": {
                "cx": "17",
                "cy": "6",
                "r": "4"
              }
            },
            {
              "tag": "path",
              "attrs": {
                "d": "M17 4v2.2l1.6.8"
              }
            },
            {
              "tag": "path",
              "attrs": {
                "d": "M4 4h2l1 10h10l.14-1M7 7h3"
              }
            }
          ],
          "strokeBased": true
        }
      ]
    }
  ]
}